cspell.json
open_alchemy/__init__.py
open_alchemy/build/MANIFEST.j2
open_alchemy/build/__init__.py
open_alchemy/build/init.j2
open_alchemy/build/init_init_open_alchemy.j2
open_alchemy/build/setup.j2
open_alchemy/cache.py
open_alchemy/cli.py
open_alchemy/column_factory/__init__.py
open_alchemy/column_factory/json.py
open_alchemy/column_factory/relationship.py
open_alchemy/column_factory/simple.py
open_alchemy/column_factory/types.py
open_alchemy/exceptions.py
open_alchemy/facades/__init__.py
open_alchemy/facades/code_formatter/__init__.py
open_alchemy/facades/jsonschema/__init__.py
open_alchemy/facades/models.py
open_alchemy/facades/sqlalchemy/__init__.py
open_alchemy/facades/sqlalchemy/json.py
open_alchemy/facades/sqlalchemy/relationship.py
open_alchemy/facades/sqlalchemy/simple.py
open_alchemy/facades/sqlalchemy/types.py
open_alchemy/helpers/__init__.py
open_alchemy/helpers/all_of.py
open_alchemy/helpers/calculate_nullable.py
open_alchemy/helpers/command.py
open_alchemy/helpers/define_all.py
open_alchemy/helpers/ext_prop/__init__.py
open_alchemy/helpers/ext_prop/common-schemas.json
open_alchemy/helpers/ext_prop/extension-schemas.json
open_alchemy/helpers/foreign_key.py
open_alchemy/helpers/inheritance.py
open_alchemy/helpers/oa_to_py_type.py
open_alchemy/helpers/peek/__init__.py
open_alchemy/helpers/peek/helpers.py
open_alchemy/helpers/property_.py
open_alchemy/helpers/ref.py
open_alchemy/helpers/relationship.py
open_alchemy/helpers/schema.py
open_alchemy/helpers/type_.py
open_alchemy/mixins.py
open_alchemy/model_factory.py
open_alchemy/models_file/__init__.py
open_alchemy/models_file/artifacts/__init__.py
open_alchemy/models_file/artifacts/args.py
open_alchemy/models_file/artifacts/column.py
open_alchemy/models_file/artifacts/type_.py
open_alchemy/models_file/artifacts/typed_dict.py
open_alchemy/models_file/model/__init__.py
open_alchemy/models_file/model/source.py
open_alchemy/models_file/model/sqlalchemy.j2
open_alchemy/models_file/model/template.j2
openalchemy-2.5.0.dist-info/entry_points.txt
openalchemy-2.5.0.dist-info/LICENSE
openalchemy-2.5.0.dist-info/WHEEL
openalchemy-2.5.0.dist-info/METADATA
openalchemy-2.5.0.dist-info/RECORD
