Metadata-Version: 2.1
Name: openalchemy
Version: 2.5.0
Summary: Maps an OpenAPI schema to SQLAlchemy models.
Home-page: https://github.com/jdkandersson/OpenAlchemy
License: Apache-2.0
Keywords: OpenAPI,SQLAlchemy,Python,models,database
Author: David Andersson
Author-email: anderssonpublic@gmail.com
Requires-Python: >=3.7,<4.0
Classifier: Development Status :: 5 - Production/Stable
Classifier: License :: OSI Approved :: Apache Software License
Classifier: Natural Language :: English
Classifier: Operating System :: OS Independent
Classifier: Programming Language :: Python :: 3
Classifier: Programming Language :: Python :: 3.7
Classifier: Programming Language :: Python :: 3.8
Classifier: Programming Language :: Python :: 3.9
Classifier: Topic :: Database
Classifier: Topic :: Database :: Front-Ends
Classifier: Topic :: Internet
Classifier: Typing :: Typed
Provides-Extra: wheel
Provides-Extra: yaml
Requires-Dist: Jinja2 (>=3,<4)
Requires-Dist: SQLAlchemy (>=1.0,<2.0)
Requires-Dist: jsonschema (>=3,<4)
Requires-Dist: sqlalchemy-stubs (>=0.3,<0.5)
Requires-Dist: typing_extensions (>=3.7.4,<4.0.0); python_version < "3.8"
Project-URL: Documentation, https://openapi-sqlalchemy.readthedocs.io/en/latest/index.html
Project-URL: Repository, https://github.com/jdkandersson/OpenAlchemy
